CONTRIBUTING.md
LICENSE.txt
MANIFEST.in
README.md
README.rst
setup.cfg
setup.py
brew/__init__.py
brew/constants.py
brew/exceptions.py
brew/grains.py
brew/hops.py
brew/parsers.py
brew/recipes.py
brew/styles.py
brew/validators.py
brew/yeasts.py
brew/cli/__init__.py
brew/cli/abv.py
brew/cli/gravity_volume.py
brew/cli/sugar.py
brew/cli/temp.py
brew/cli/yeast.py
brew/utilities/__init__.py
brew/utilities/abv.py
brew/utilities/color.py
brew/utilities/efficiency.py
brew/utilities/hops.py
brew/utilities/malt.py
brew/utilities/sugar.py
brew/utilities/temperature.py
brew/utilities/yeast.py
brewday.egg-info/PKG-INFO
brewday.egg-info/SOURCES.txt
brewday.egg-info/dependency_links.txt
brewday.egg-info/entry_points.txt
brewday.egg-info/top_level.txt
brewday.egg-info/zip-safe
data/__init__.py
data/__main__.py
examples/README.md
examples/enzymatic_rests.py
examples/pale_ale_builder.py
examples/pale_ale_builder2.py
examples/pale_ale_parser.py
examples/pale_ale_recipe.py
examples/styles.py
examples/brewing_classic_styles/biere_de_linde_dict.py
examples/brewing_classic_styles/munich_madness_dict.py
examples/brewing_classic_styles/raison_de_saison_dict.py
examples/oak_barrel_winecraft/kolsch_ale_dict.py
examples/the_brew_shop/10_pound_stout.py
examples/the_brew_shop/irish_red.py
examples/the_brew_shop/scottish_amber.py
examples/the_brew_shop/yellow_moon_ipa.py
tests/fixtures.py
tests/nose.cfg
tests/test_cli_abv.py
tests/test_cli_gravity_volume.py
tests/test_cli_sugar.py
tests/test_cli_temp.py
tests/test_cli_yeast.py
tests/test_grains.py
tests/test_hops.py
tests/test_parsers.py
tests/test_recipes.py
tests/test_recipes_extract.py
tests/test_recipes_imperial.py
tests/test_recipes_si.py
tests/test_styles.py
tests/test_utilities_abv.py
tests/test_utilities_color.py
tests/test_utilities_efficiency.py
tests/test_utilities_hops.py
tests/test_utilities_malt.py
tests/test_utilities_sugar.py
tests/test_utilities_temperature.py
tests/test_utilities_yeast.py
tests/test_validators.py
tests/test_yeasts.py