Metadata-Version: 1.1
Name: brewday
Version: 1.0.0
Summary: Brew Day Tools
Home-page: https://github.com/chrisgilmerproj/brewday
Author: Chris Gilmer
Author-email: chris.gilmer@gmail.com
License: MIT
Download-URL: https://github.com/chrisgilmerproj/brewday/tarball/1.0.0
Keywords: brew brewing beer grain hops yeast alcohol
Platform: UNKNOWN
Classifier: Development Status :: 3 - Alpha
Classifier: Intended Audience :: Developers
Classifier: Intended Audience :: Education
Classifier: Intended Audience :: Science/Research
Classifier: Intended Audience :: Other Audience
Classifier: License :: OSI Approved :: MIT License
Classifier: Operating System :: OS Independent
Classifier: Programming Language :: Python
Classifier: Programming Language :: Python :: 2
Classifier: Programming Language :: Python :: 2.7
Classifier: Programming Language :: Python :: 3
Classifier: Programming Language :: Python :: 3.3
Classifier: Programming Language :: Python :: 3.4
Classifier: Programming Language :: Python :: 3.5
Classifier: Programming Language :: Python :: 3.6
Classifier: Topic :: Software Development :: Libraries :: Python Modules
